setup.py
prob_distribution_methods/Binomialdistribution.py
prob_distribution_methods/Gaussiandistribution.py
prob_distribution_methods/Generaldistribution.py
prob_distribution_methods/__init__.py
prob_distribution_methods.egg-info/PKG-INFO
prob_distribution_methods.egg-info/SOURCES.txt
prob_distribution_methods.egg-info/dependency_links.txt
prob_distribution_methods.egg-info/not-zip-safe
prob_distribution_methods.egg-info/top_level.txt