Metadata-Version: 1.0
Name: prob-distribution-methods
Version: 1.0
Summary: Truong test the distributions to pypi.org
Home-page: UNKNOWN
Author: Truong LE
Author-email: lqtruong@gmail.com
License: UNKNOWN
Platform: UNKNOWN
